vallignus/__init__.py
vallignus/auth.py
vallignus/cli.py
vallignus/logger.py
vallignus/proxy.py
vallignus/rules.py
vallignus/sessions.py
vallignus/identity/__init__.py
vallignus/identity/chrome.py
vallignus/identity/manager.py
vallignus-0.4.2.dist-info/METADATA
vallignus-0.4.2.dist-info/WHEEL
vallignus-0.4.2.dist-info/entry_points.txt
vallignus-0.4.2.dist-info/top_level.txt
vallignus-0.4.2.dist-info/RECORD
