Metadata-Version: 2.4
Name: vallignus
Version: 0.4.2
Summary: Local runtime for AI agents: sessions, replay, and hard caps
Author-email: Jacob Gadek <your.email@example.com>
License: MIT
Project-URL: Repository, https://github.com/jacobgadek/vallignus
Keywords: ai,agent,runtime,sessions,replay,limits,llm
Requires-Python: >=3.8
Requires-Dist: browser-cookie3
Requires-Dist: click
Requires-Dist: mitmproxy<10.0.0,>=9.0.0
Requires-Dist: rich
Requires-Dist: cryptography>=38.0.0
Provides-Extra: dev
Requires-Dist: pytest>=7.0.0; extra == "dev"
